<annotation>
	<folder>JPEGImages</folder>
	<filename>wen2_181018_0098.jpg</filename>
	<path>C:\pythonwork\keras-yolo3-master\VOC\JPEGImages\wen2_181018_0098.jpg</path>
	<source>
		<database>Unknown</database>
	</source>
	<size>
		<width>1536</width>
		<height>2730</height>
		<depth>3</depth>
	</size>
	<segmented>0</segmented>
	<object>
		<name>second</name>
		<pose>Unspecified</pose>
		<truncated>1</truncated>
		<difficult>0</difficult>
		<bndbox>
			<xmin>418</xmin>
			<ymin>750</ymin>
			<xmax>1280</xmax>
			<ymax>2730</ymax>
		</bndbox>
	</object>
</annotation>
